pymakergame/__init__.py
pymakergame/main.py
pymakergame-0.4.dist-info/METADATA
pymakergame-0.4.dist-info/WHEEL
pymakergame-0.4.dist-info/top_level.txt
pymakergame-0.4.dist-info/RECORD
