Metadata-Version: 2.1
Name: pymakergame
Version: 0.4
Summary: Python Library That Makes Pygame Easy
Author-email: GaelHF <gael.31.hf@gmail.com>
Project-URL: Homepage, https://github.com/GaelHF/pymakergame
Project-URL: Issues, https://github.com/GaelHF/pymakergame/issues
Classifier: Programming Language :: Python :: 3
Classifier: License :: OSI Approved :: MIT License
Classifier: Operating System :: OS Independent
Requires-Python: >=3.8
